planetary_coverage/__init__.py
planetary_coverage/__version__.py
planetary_coverage/cli/__init__.py
planetary_coverage/cli/kernel.py
planetary_coverage/cli/metakernel.py
planetary_coverage/debug/__init__.py
planetary_coverage/esa/__init__.py
planetary_coverage/esa/api.py
planetary_coverage/esa/export.py
planetary_coverage/esa/metakernel.py
planetary_coverage/esa/vars.py
planetary_coverage/events/__init__.py
planetary_coverage/events/csv.py
planetary_coverage/events/event.py
planetary_coverage/events/evf.py
planetary_coverage/events/file.py
planetary_coverage/events/itl.py
planetary_coverage/events/orb.py
planetary_coverage/html/__init__.py
planetary_coverage/html/formatter.py
planetary_coverage/maps/__init__.py
planetary_coverage/maps/data/.gitignore
planetary_coverage/maps/data/Callisto.jpg
planetary_coverage/maps/data/Charon.jpg
planetary_coverage/maps/data/Earth.jpg
planetary_coverage/maps/data/Enceladus.jpg
planetary_coverage/maps/data/Europa.jpg
planetary_coverage/maps/data/Ganymede.jpg
planetary_coverage/maps/data/Io.jpg
planetary_coverage/maps/data/Jupiter.jpg
planetary_coverage/maps/data/Mars.jpg
planetary_coverage/maps/data/Mercury.jpg
planetary_coverage/maps/data/Moon.jpg
planetary_coverage/maps/data/Neptune.jpg
planetary_coverage/maps/data/Pluto.jpg
planetary_coverage/maps/data/README.md
planetary_coverage/maps/data/Saturn.jpg
planetary_coverage/maps/data/Titan.jpg
planetary_coverage/maps/data/Uranus.jpg
planetary_coverage/maps/data/Venus.jpg
planetary_coverage/maps/map.py
planetary_coverage/math/__init__.py
planetary_coverage/math/greatcircle.py
planetary_coverage/math/sphere.py
planetary_coverage/math/vectors.py
planetary_coverage/misc/__init__.py
planetary_coverage/misc/cache.py
planetary_coverage/misc/depreciation.py
planetary_coverage/misc/dotenv.py
planetary_coverage/misc/download.py
planetary_coverage/misc/filesize.py
planetary_coverage/misc/ipython.py
planetary_coverage/misc/list.py
planetary_coverage/misc/logger.py
planetary_coverage-1.2.1.dist-info/METADATA
planetary_coverage-1.2.1.dist-info/WHEEL
planetary_coverage-1.2.1.dist-info/entry_points.txt
planetary_coverage-1.2.1.dist-info/licenses/LICENSE.md
planetary_coverage-1.2.1.dist-info/RECORD
