Metadata-Version: 2.4
Name: planetary-coverage
Version: 1.2.1
Summary: Planetary coverage package
License: BSD 3-Clause License
License-File: LICENSE.md
Keywords: planetary,coverage,spice,esa,juice
Author: Seignovert et al.
Author-email: contact@planetary-coverage.org
Requires-Python: >=3.11,<4.0
Classifier: Development Status :: 5 - Production/Stable
Classifier: Intended Audience :: Developers
Classifier: Intended Audience :: Science/Research
Classifier: License :: OSI Approved :: BSD License
Classifier: Natural Language :: English
Classifier: Programming Language :: Python
Classifier: Programming Language :: Python :: 3
Classifier: Programming Language :: Python :: 3.11
Classifier: Programming Language :: Python :: 3.12
Classifier: Programming Language :: Python :: 3.13
Classifier: Topic :: Scientific/Engineering
Classifier: Topic :: Scientific/Engineering :: Astronomy
Classifier: Topic :: Scientific/Engineering :: Atmospheric Science
Provides-Extra: juice
Requires-Dist: certifi (>=2025)
Requires-Dist: defusedxml (>=0.7.1)
Requires-Dist: esa-ptr (>=1.4) ; extra == "juice"
Requires-Dist: matplotlib (>=3.10)
Requires-Dist: numpy (>=1.26)
Requires-Dist: pillow (>=11)
Requires-Dist: spiceypy (>=6.0)
Project-URL: Bug Tracker, https://gitlab.esa.int/juice-soc-public/python/planetary-coverage/-/issues
Project-URL: Changelog, https://docs.planetary-coverage.org/latest/CHANGELOG.html
Project-URL: Documentation, https://docs.planetary-coverage.org
Project-URL: Repository, https://gitlab.esa.int/juice-soc-public/python/planetary-coverage
